[
	{
		"id": 0,
		"title": "Научно-Технический Центр \"ПромТех\"",
		"keys": [
			"НТЦ \"ПромТех\"",
			"ПромТех",
			"НТЦПТ",
			"PromTech",
			"НТЦ Пром-Тех"
		]
	},
	{
		"id": 1,
		"title": "Объединение \"ЭкоБудущее\"",
		"keys": [
			"ЭкоБудущее",
			"Объединение ЭБ",
			"ЭБ",
			"EcoFuture Russia"
		]
	},
	{
		"id": 2,
		"title": "Центр Правовой Поддержки \"Щит\"",
		"keys": [
			"ЦПП \"Щит\"",
			"Щит",
			"Центр \"Щит\"",
			"ЦПП-Щит",
			"CPP Shchit"
		]
	},
	{
		"id": 3,
		"title": "Ассоциация Развития Цифровых Технологий",
		"keys": [
			"АРЦТ",
			"Ассоциация Цифра",
			"DigitalTech Russia",
			"АРЦТех",
			"Ассоциация Развития ЦТ"
		]
	},
	{
		"id": 4,
		"title": "Институт Гуманитарных Инициатив",
		"keys": [
			"ИГИ",
			"Институт ИГИ",
			"Гуманитарный Институт",
			"IGI Russia",
			"Институт ГИ"
		]
	}
]